<?xml version="1.0" encoding="UTF-8"?>
<MetaDataObject xmlns="http://v8.1c.ru/8.3/MDClasses" xmlns:app="http://v8.1c.ru/8.2/managed-application/core" xmlns:cfg="http://v8.1c.ru/8.1/data/enterprise/current-config" xmlns:cmi="http://v8.1c.ru/8.2/managed-application/cmi" xmlns:ent="http://v8.1c.ru/8.1/data/enterprise" xmlns:lf="http://v8.1c.ru/8.2/managed-application/logform" xmlns:style="http://v8.1c.ru/8.1/data/ui/style" xmlns:sys="http://v8.1c.ru/8.1/data/ui/fonts/system" xmlns:v8="http://v8.1c.ru/8.1/data/core" xmlns:v8ui="http://v8.1c.ru/8.1/data/ui" xmlns:web="http://v8.1c.ru/8.1/data/ui/colors/web" xmlns:win="http://v8.1c.ru/8.1/data/ui/colors/windows" xmlns:xen="http://v8.1c.ru/8.3/xcf/enums" xmlns:xpr="http://v8.1c.ru/8.3/xcf/predef" xmlns:xr="http://v8.1c.ru/8.3/xcf/readable" xmlns:xs="http://www.w3.org/2001/XMLSchema" xmlns:xsi="http://www.w3.org/2001/XMLSchema-instance" version="2.20">
	<CommonCommand uuid="9b68dec3-4d60-4c20-9058-2d4d6bb07b4f">
		<Properties>
			<Name>ХМ_СообщитьID</Name>
			<Synonym>
				<v8:item>
					<v8:lang>ru</v8:lang>
					<v8:content>Сообщить ID</v8:content>
				</v8:item>
			</Synonym>
			<Comment/>
			<Group>CommandGroup.ХМ_Каспер</Group>
			<Representation>Auto</Representation>
			<ToolTip/>
			<Picture/>
			<Shortcut/>
			<IncludeHelpInContents>false</IncludeHelpInContents>
			<CommandParameterType>
				<v8:Type>cfg:DocumentRef.уп_ЗаявлениеОНаличииПравопреемниковНПО</v8:Type>
				<v8:Type>cfg:DocumentRef.ХМ_СправкаОСтраховомСтаже</v8:Type>
				<v8:Type>cfg:DocumentRef.уп_ДополнительноеСоглашение</v8:Type>
				<v8:Type>cfg:DocumentRef.уп_ЗакрытиеДоговораОПС</v8:Type>
				<v8:Type>cfg:DocumentRef.уп_ВозвратПенсийОПС</v8:Type>
				<v8:Type>cfg:DocumentRef.уп_РешениеОПереводеСредствВРезервОПС</v8:Type>
				<v8:Type>cfg:DocumentRef.уп_ЗаявлениеЗЛОНазначенииСрочнойВыплаты</v8:Type>
				<v8:Type>cfg:DocumentRef.уп_ЗаявлениеЗЛОЕдиновременнойВыплате</v8:Type>
				<v8:Type>cfg:DocumentRef.уп_ПеремещениеПенсионныхРезервов</v8:Type>
				<v8:Type>cfg:DocumentRef.уп_СправкаОбУплатеВзносовНПО</v8:Type>
				<v8:Type>cfg:DocumentRef.уп_РешениеОВосстановленииВыплатыНП</v8:Type>
				<v8:Type>cfg:DocumentRef.уп_РешениеОПереводеСредствСПНвПДС</v8:Type>
				<v8:Type>cfg:DocumentRef.уп_НачислениеПенсий</v8:Type>
				<v8:Type>cfg:DocumentRef.уп_РегистрацияПолучателейОПС</v8:Type>
				<v8:Type>cfg:DocumentRef.уп_НачислениеНДФЛ</v8:Type>
				<v8:Type>cfg:CatalogRef.уп_ПенсионныеСчета</v8:Type>
				<v8:Type>cfg:CatalogRef.уп_ПенсионныеДоговоры</v8:Type>
				<v8:Type>cfg:DocumentRef.уп_НачислениеПенсийОПС</v8:Type>
				<v8:Type>cfg:DocumentRef.уп_СообщениеОЗаключенииПрекращенииДоговора</v8:Type>
				<v8:Type>cfg:DocumentRef.уп_РаспределениеВзносов</v8:Type>
				<v8:Type>cfg:DocumentRef.уп_ПриостановкаВыплат</v8:Type>
				<v8:Type>cfg:DocumentRef.уп_ЗаявлениеУчастникаОРасторженииНПО</v8:Type>
				<v8:Type>cfg:DocumentRef.уп_РаспределениеИД</v8:Type>
				<v8:Type>cfg:DocumentRef.уп_ЗаявлениеНаПредоставлениеВычетов</v8:Type>
				<v8:Type>cfg:DocumentRef.уп_ЗаявлениеУчастникаОНазначенииПенсии</v8:Type>
				<v8:Type>cfg:DocumentRef.хм_РаспоряжениеНаПроведениеУдержаний</v8:Type>
				<v8:Type>cfg:DocumentRef.уп_РешениеОбОтказеВВыплатеСредствПенсионныхНакоплений</v8:Type>
				<v8:Type>cfg:DocumentRef.уп_ВыплатныеРеестры</v8:Type>
				<v8:Type>cfg:DocumentRef.уп_ЗакрытиеДоговораВкладчиком</v8:Type>
				<v8:Type>cfg:DocumentRef.уп_РешениеОбОтказеСВ</v8:Type>
				<v8:Type>cfg:DocumentRef.уп_ИзменениеРазмеровПенсионныхВыплат</v8:Type>
				<v8:Type>cfg:DocumentRef.уп_ВозвратПенсий</v8:Type>
				<v8:Type>cfg:DocumentRef.ХМ_ЗаявленияДСВ</v8:Type>
				<v8:Type>cfg:DocumentRef.уп_ЗаявлениеЗЛОНазначенииНЧТП</v8:Type>
				<v8:Type>cfg:DocumentRef.уп_ЗаявлениеПравопреемникаОВыплатеОПС</v8:Type>
				<v8:Type>cfg:DocumentRef.уп_РешениеОбОтказеНЧТП</v8:Type>
				<v8:Type>cfg:DocumentRef.пдс_РешениеОНазначенииПериодическойВыплаты</v8:Type>
				<v8:Type>cfg:DocumentRef.уп_ВозвратПрочихНачисленийОПС</v8:Type>
				<v8:Type>cfg:DocumentRef.уп_ЗаявлениеОЕдиновременномВзносе</v8:Type>
				<v8:Type>cfg:DocumentRef.уп_НачислениеРезервов</v8:Type>
				<v8:Type>cfg:DocumentRef.пдс_ОткрытиеДоговораПДС</v8:Type>
				<v8:Type>cfg:DocumentRef.уп_ИндексацияСрочнойВыплаты</v8:Type>
				<v8:Type>cfg:DocumentRef.уп_ЗакрытиеСчетов</v8:Type>
				<v8:Type>cfg:DocumentRef.ХМ_ПрекращениеВыплатыПенсии</v8:Type>
				<v8:Type>cfg:DocumentRef.уп_Регламент</v8:Type>
				<v8:Type>cfg:DocumentRef.уп_ИсполнительныйЛист</v8:Type>
				<v8:Type>cfg:DocumentRef.уп_ПерерасчетПоПоступившемуВзносу</v8:Type>
				<v8:Type>cfg:DocumentRef.хм_РегистрацияОплатыИзлишнеВыплаченныхСуммНПО</v8:Type>
				<v8:Type>cfg:DocumentRef.уп_ЗаявлениеПравопреемникаОВыплатеНПО</v8:Type>
				<v8:Type>cfg:DocumentRef.уп_ЗаявлениеПравопреемникаОбОтказеОПС</v8:Type>
				<v8:Type>cfg:DocumentRef.уп_ОткрытиеДоговораОПС</v8:Type>
				<v8:Type>cfg:DocumentRef.ПоступлениеНаРасчетныйСчет</v8:Type>
				<v8:Type>cfg:DocumentRef.уп_ПодтверждениеПФР</v8:Type>
				<v8:Type>cfg:DocumentRef.пдс_СправкаОбУплатеВзносовПДС</v8:Type>
				<v8:Type>cfg:DocumentRef.уп_Распоряжение</v8:Type>
				<v8:Type>cfg:DocumentRef.уп_ПеререгистрацияУчастника</v8:Type>
				<v8:Type>cfg:DocumentRef.уп_ПерераспределениеСредствНПО</v8:Type>
				<v8:Type>cfg:DocumentRef.уп_РегистрацияСмертиУчастников</v8:Type>
				<v8:Type>cfg:DocumentRef.уп_РешениеОЕдиновременнойВыплате</v8:Type>
				<v8:Type>cfg:DocumentRef.уп_РешениеОбОтказеВЕдиновременнойВыплате</v8:Type>
				<v8:Type>cfg:DocumentRef.уп_ПриостановкаВыплатОПС</v8:Type>
				<v8:Type>cfg:DocumentRef.уп_РешениеОВыплатеСредствПНИзРезерваФондаПоОПС</v8:Type>
				<v8:Type>cfg:DocumentRef.уп_ПоступлениеВзносов</v8:Type>
				<v8:Type>cfg:DocumentRef.уп_ОткрытиеДоговора</v8:Type>
				<v8:Type>cfg:DocumentRef.уп_ЗаявлениеОНаличииПравопреемников</v8:Type>
				<v8:Type>cfg:DocumentRef.уп_РешениеОНазначенииСрочнойВыплаты</v8:Type>
				<v8:Type>cfg:DocumentRef.уп_РаспределениеИДОПС</v8:Type>
				<v8:Type>cfg:DocumentRef.уп_РегистрацияПоступленийОПС</v8:Type>
				<v8:Type>cfg:DocumentRef.пдс_ПоступлениеВзносовПДС</v8:Type>
				<v8:Type>cfg:DocumentRef.ХМ_pf_fond_npf_pfr</v8:Type>
				<v8:Type>cfg:DocumentRef.уп_ИндексацияНЧТП</v8:Type>
				<v8:Type>cfg:DocumentRef.уп_РешениеОВыплатеСредствПенсионныхНакоплений</v8:Type>
				<v8:Type>cfg:DocumentRef.уп_РешениеОНазначенииНЧТП</v8:Type>
				<v8:Type>cfg:DocumentRef.уп_ИзменениеРазмеровВыплатОПС</v8:Type>
			</CommandParameterType>
			<ParameterUseMode>Multiple</ParameterUseMode>
			<ModifiesData>true</ModifiesData>
			<OnMainServerUnavalableBehavior>Auto</OnMainServerUnavalableBehavior>
		</Properties>
	</CommonCommand>
</MetaDataObject>